log_signatures_pytorch/__init__.py
log_signatures_pytorch/bch_coefficients.py
log_signatures_pytorch/hall_bch.py
log_signatures_pytorch/hall_projection.py
log_signatures_pytorch/log_signature.py
log_signatures_pytorch/lyndon_words.py
log_signatures_pytorch/signature.py
log_signatures_pytorch/sparse_signature.py
log_signatures_pytorch/tensor_ops.py
log_signatures_pytorch-0.1.11.dist-info/WHEEL
log_signatures_pytorch-0.1.11.dist-info/METADATA
log_signatures_pytorch-0.1.11.dist-info/RECORD
