Metadata-Version: 2.3
Name: log-signatures-pytorch
Version: 0.1.11
Summary: Simple pytorch implementation of log-signatures.
Author: Erlend Aune
Author-email: Erlend Aune <erlend.aune@pm.me>
License: MIT License
Requires-Dist: torch>=2.9.1
Requires-Python: >=3.13
Project-URL: Homepage, https://github.com/froskekongen/log_signatures_pytorch
Project-URL: Repository, https://github.com/froskekongen/log_signatures_pytorch
Project-URL: Documentation, https://froskekongen.github.io/log_signatures_pytorch/
